README.md
setup.cfg
setup.py
onnx_chainer/__init__.py
onnx_chainer/context.py
onnx_chainer/export.py
onnx_chainer/export_testcase.py
onnx_chainer/graph.py
onnx_chainer/mapping.py
onnx_chainer/onnx_helper.py
onnx_chainer/replace_func.py
onnx_chainer.egg-info/PKG-INFO
onnx_chainer.egg-info/SOURCES.txt
onnx_chainer.egg-info/dependency_links.txt
onnx_chainer.egg-info/requires.txt
onnx_chainer.egg-info/top_level.txt
onnx_chainer/functions/__init__.py
onnx_chainer/functions/activation.py
onnx_chainer/functions/array.py
onnx_chainer/functions/connection.py
onnx_chainer/functions/converter.py
onnx_chainer/functions/loss.py
onnx_chainer/functions/math.py
onnx_chainer/functions/noise.py
onnx_chainer/functions/normalization.py
onnx_chainer/functions/opset_version.py
onnx_chainer/functions/pooling.py
onnx_chainer/testing/__init__.py
onnx_chainer/testing/get_test_data_set.py
onnx_chainer/testing/input_generator.py
onnx_chainer/testing/test_mxnet.py
onnx_chainer/testing/test_onnxruntime.py