Metadata-Version: 2.1
Name: onnx-chainer
Version: 1.6.0
Summary: Convert a Chainer model into ONNX
Home-page: https://github.com/chainer/onnx-chainer
Author: Shunta Saito
Author-email: shunta@preferred.jp
License: MIT License
Keywords: ONNX Chainer model converter deep learning
Platform: UNKNOWN
Provides-Extra: stylecheck
Provides-Extra: test
Provides-Extra: test-cpu
Provides-Extra: test-gpu
Provides-Extra: doctest
Provides-Extra: travis
Provides-Extra: flexci
